multiplier.v
module multiplier(out, a_in, b_in, clk, start, reset, finish, bcd);

parameter N = 8;

// Outputs
output [(((N*2)/3)+1)*4-1:0] bcd;
output [(N*2)-1:0] out;
output finish;

// Inputs
input start;
input clk;
input reset;
input [N-1:0] a_in;
input [N-1:0] b_in;


// Internal registers
reg [(((N*2)/3)+1)*4-1:0] bcd_reg = 0;
reg [(N*2)-1:0] out_reg;
reg finish_reg = 0;

reg [(N*2)-1:0] a_in_reg;
reg [(N*2)-1:0] b_in_reg;

// Counter for multiplication cycles
reg [N:0] bits;


// Output assignments
assign bcd = bcd_reg;
assign out = out_reg;
assign finish = finish_reg;

integer i;


// Reset internal registers
always @(negedge reset)
begin
    out_reg = 0;
    a_in_reg = 0;
    b_in_reg = 0;
end


// Sequential multiplication process
always @(posedge clk)
begin

    if (!reset)
    begin

        case(start)

            // Load input operands
            1'b0:
            begin
                a_in_reg = a_in;
                b_in_reg = b_in;
                bits = N;

                finish_reg = 0;
                out_reg = 0;
                bcd_reg = 0;

                $display("Value loaded into the input register.");
            end


            // Shift-and-add multiplication
            1'b1:
            begin

                // Add multiplicand when LSB of multiplier is 1
                if (b_in_reg[0] == 1)
                begin
                    out_reg = out_reg + a_in_reg;
                end

                // Move to the next multiplier bit
                bits = bits - 1;
                a_in_reg = a_in_reg << 1;
                b_in_reg = b_in_reg >> 1;

            end

        endcase


        // Multiplication completed
        if (bits == 0)
        begin

            $display("Multiplication Completed");

            finish_reg = 1'b1;


            // Binary to BCD conversion
            for(i = 0; i < (N*2); i = i + 1)
            begin

                if(3 <= ((N*2)/3+1)*4-1 &&
                   bcd_reg[3:0] >= 5)
                    bcd_reg[3:0] = bcd_reg[3:0] + 3;

                if(7 <= ((N*2)/3+1)*4-1 &&
                   bcd_reg[7:4] >= 5)
                    bcd_reg[7:4] = bcd_reg[7:4] + 3;

                if(11 <= ((N*2)/3+1)*4-1 &&
                   bcd_reg[11:8] >= 5)
                    bcd_reg[11:8] = bcd_reg[11:8] + 3;

                if(15 <= ((N*2)/3+1)*4-1 &&
                   bcd_reg[15:12] >= 5)
                    bcd_reg[15:12] = bcd_reg[15:12] + 3;

                // Shift binary result into BCD register
                bcd_reg = {
                    bcd_reg[(((N*2)/3)+1)*4-2:0],
                    out_reg[(N*2)-1-i]
                };

            end

            $display("Conversion of binary to BCD Completed");

        end

    end

end

endmodule

multiplier_tb.v
module multiplier_tb;

parameter n_bits = 5;

// Inputs
reg [n_bits-1:0] a_in;
reg [n_bits-1:0] b_in;
reg clk;
reg start;
reg reset;

// Outputs
wire [(n_bits*2)-1:0] out;
wire finish;
wire [(((n_bits*2)/3)+1)*4-1:0] bcd;


// Instantiate the multiplier
multiplier uut(
    .out(out),
    .a_in(a_in),
    .b_in(b_in),
    .clk(clk),
    .start(start),
    .reset(reset),
    .finish(finish),
    .bcd(bcd)
);

defparam uut.N = n_bits;


// Clock generation
initial
begin
    forever
        #50 clk = ~clk;
end


// Test sequence
initial
begin

    // Initialize inputs
    a_in = 0;
    b_in = 0;
    clk = 0;
    start = 0;
    reset = 0;

    // Wait for reset
    #100;

    // First multiplication: 26 x 30
    a_in = 'd26;
    b_in = 'd30;
    start = 0;

    #200;
    start = 1;

    // Second multiplication: 13 x 13
    #1000;
    a_in = 'd13;
    b_in = 'd13;
    start = 0;

    #200;
    start = 1;

end


// End simulation
initial
begin
    #3000;
    $finish;
end


// VCD waveform generation
initial
begin
    $dumpfile("multiplier.vcd");
    $dumpvars(0, multiplier_tb);
end

endmodule

multiplier.vcd
$date
	Mon Aug 24 20:46:58 2026
$end
$version
	Icarus Verilog
$end
$timescale
	1s
$end
$scope module multiplier_tb $end
$var wire 10 ! out [9:0] $end
$var wire 1 " finish $end
$var wire 16 # bcd [15:0] $end
$var parameter 32 $ n_bits $end
$var reg 5 % a_in [4:0] $end
$var reg 5 & b_in [4:0] $end
$var reg 1 ' clk $end
$var reg 1 ( reset $end
$var reg 1 ) start $end
$scope module uut $end
$var wire 5 * a_in [4:0] $end
$var wire 5 + b_in [4:0] $end
$var wire 16 , bcd [15:0] $end
$var wire 1 ' clk $end
$var wire 1 " finish $end
$var wire 10 - out [9:0] $end
$var wire 1 ( reset $end
$var wire 1 ) start $end
$var parameter 32 . N $end
$var reg 10 / a_in_reg [9:0] $end
$var reg 10 0 b_in_reg [9:0] $end
$var reg 16 1 bcd_reg [15:0] $end
$var reg 6 2 bits [5:0] $end
$var reg 1 3 finish_reg $end
$var reg 10 4 out_reg [9:0] $end
$var integer 32 5 i [31:0] $end
$upscope $end
$upscope $end
$enddefinitions $end
$comment Show the parameter values. $end
$dumpall
b101 .
b101 $
$end
#0
$dumpvars
bx 5
b0 4
03
bx 2
b0 1
b0 0
b0 /
b0 -
b0 ,
b0 +
b0 *
0)
0(
0'
b0 &
b0 %
b0 #
0"
b0 !
$end
#50
b101 2
1'
#100
0'
b11110 &
b11110 +
b11010 %
b11010 *
#150
b11110 0
b11010 /
1'
#200
0'
#250
1'
#300
0'
1)
#350
b1111 0
b110100 /
b100 2
1'
#400
0'
#450
b111 0
b1101000 /
b11 2
b110100 !
b110100 -
b110100 4
1'
#500
0'
#550
b11 0
b11010000 /
b10 2
b10011100 !
b10011100 -
b10011100 4
1'
#600
0'
#650
b1 0
b110100000 /
b1 2
b101101100 !
b101101100 -
b101101100 4
1'
#700
0'
#750
b11110000000 #
b11110000000 ,
b11110000000 1
b1010 5
1"
13
b0 0
b1101000000 /
b0 2
b1100001100 !
b1100001100 -
b1100001100 4
1'
#800
0'
#850
b1010000000 /
b111111 2
1'
#900
0'
#950
b100000000 /
b111110 2
1'
#1000
0'
#1050
b1000000000 /
b111101 2
1'
#1100
0'
#1150
b0 /
b111100 2
1'
#1200
0'
#1250
b111011 2
1'
#1300
0'
0)
b1101 &
b1101 +
b1101 %
b1101 *
#1350
b0 #
b0 ,
b0 1
b0 !
b0 -
b0 4
0"
03
b101 2
b1101 0
b1101 /
1'
#1400
0'
#1450
1'
#1500
0'
1)
#1550
b110 0
b11010 /
b100 2
b1101 !
b1101 -
b1101 4
1'
#1600
0'
#1650
b11 0
b110100 /
b11 2
1'
#1700
0'
#1750
b1 0
b1101000 /
b10 2
b1000001 !
b1000001 -
b1000001 4
1'
#1800
0'
#1850
b0 0
b11010000 /
b1 2
b10101001 !
b10101001 -
b10101001 4
1'
#1900
0'
#1950
b101101001 #
b101101001 ,
b101101001 1
b1010 5
1"
13
b110100000 /
b0 2
1'
#2000
0'
#2050
b1101000000 /
b111111 2
1'
#2100
0'
#2150
b1010000000 /
b111110 2
1'
#2200
0'
#2250
b100000000 /
b111101 2
1'
#2300
0'
#2350
b1000000000 /
b111100 2
1'
#2400
0'
#2450
b0 /
b111011 2
1'
#2500
0'
#2550
b111010 2
1'
#2600
0'
#2650
b111001 2
1'
#2700
0'
#2750
b111000 2
1'
#2800
0'
#2850
b110111 2
1'
#2900
0'
#2950
b110110 2
1'
